AminoZ/__init__.py
AminoZ/client.py
AminoZ-0.1.1.dist-info/LICENSE
AminoZ-0.1.1.dist-info/METADATA
AminoZ-0.1.1.dist-info/WHEEL
AminoZ-0.1.1.dist-info/top_level.txt
AminoZ-0.1.1.dist-info/RECORD
